Metadata-Version: 2.1
Name: fpy-datareader
Version: 0.1.0
Summary: Remote data access to government data for pandas.
Author: well-living
License: MIT
Platform: UNKNOWN
License-File: LICENSE
